hdmf/__init__.py
hdmf/_due.py
hdmf/_version.py
hdmf/container.py
hdmf/data_utils.py
hdmf/monitor.py
hdmf/query.py
hdmf/term_set.py
hdmf/utils.py
hdmf/backends/__init__.py
hdmf/backends/errors.py
hdmf/backends/io.py
hdmf/backends/utils.py
hdmf/backends/warnings.py
hdmf/backends/hdf5/__init__.py
hdmf/backends/hdf5/h5_utils.py
hdmf/backends/hdf5/h5tools.py
hdmf/build/__init__.py
hdmf/build/builders.py
hdmf/build/classgenerator.py
hdmf/build/errors.py
hdmf/build/manager.py
hdmf/build/objectmapper.py
hdmf/build/warnings.py
hdmf/common/__init__.py
hdmf/common/alignedtable.py
hdmf/common/hierarchicaltable.py
hdmf/common/multi.py
hdmf/common/resources.py
hdmf/common/sparse.py
hdmf/common/table.py
hdmf/common/hdmf-common-schema/.codespellrc
hdmf/common/hdmf-common-schema/Legal.txt
hdmf/common/hdmf-common-schema/README.md
hdmf/common/hdmf-common-schema/license.txt
hdmf/common/hdmf-common-schema/requirements-doc.txt
hdmf/common/hdmf-common-schema/setup.cfg
hdmf/common/hdmf-common-schema/common/base.yaml
hdmf/common/hdmf-common-schema/common/experimental.yaml
hdmf/common/hdmf-common-schema/common/namespace.yaml
hdmf/common/hdmf-common-schema/common/resources.yaml
hdmf/common/hdmf-common-schema/common/sparse.yaml
hdmf/common/hdmf-common-schema/common/table.yaml
hdmf/common/hdmf-common-schema/docs/Makefile
hdmf/common/hdmf-common-schema/docs/Readme.md
hdmf/common/hdmf-common-schema/docs/make.bat
hdmf/common/hdmf-common-schema/docs/source/conf.py
hdmf/common/hdmf-common-schema/docs/source/conf_doc_autogen.py
hdmf/common/hdmf-common-schema/docs/source/credits.rst
hdmf/common/hdmf-common-schema/docs/source/format.rst
hdmf/common/hdmf-common-schema/docs/source/format_description.rst
hdmf/common/hdmf-common-schema/docs/source/format_release_notes.rst
hdmf/common/hdmf-common-schema/docs/source/hdmf_common_release_notes.rst
hdmf/common/hdmf-common-schema/docs/source/hdmf_experimental_release_notes.rst
hdmf/common/hdmf-common-schema/docs/source/index.rst
hdmf-4.2.0.dist-info/METADATA
hdmf-4.2.0.dist-info/WHEEL
hdmf-4.2.0.dist-info/entry_points.txt
hdmf-4.2.0.dist-info/RECORD
