Metadata-Version: 2.4
Name: hdmf
Version: 4.2.0
Summary: A hierarchical data modeling framework for modern science data standards
Project-URL: Homepage, https://github.com/hdmf-dev/hdmf
Project-URL: Bug Tracker, https://github.com/hdmf-dev/hdmf/issues
Author-email: Ryan Ly <rly@lbl.gov>, Andrew Tritt <ajtritt@lbl.gov>, Oliver Ruebel <oruebel@lbl.gov>, Ben Dichter <ben.dichter@gmail.com>, Matthew Avaylon <mavaylon@lbl.gov>
License-Expression: BSD-3-Clause
Classifier: Development Status :: 5 - Production/Stable
Classifier: Intended Audience :: Developers
Classifier: Intended Audience :: Science/Research
Classifier: License :: OSI Approved :: BSD License
Classifier: Operating System :: OS Independent
Classifier: Programming Language :: Python
Classifier: Programming Language :: Python :: 3.9
Classifier: Programming Language :: Python :: 3.10
Classifier: Programming Language :: Python :: 3.11
Classifier: Programming Language :: Python :: 3.12
Classifier: Programming Language :: Python :: 3.13
Classifier: Topic :: Scientific/Engineering :: Medical Science Apps.
Requires-Python: >=3.9
Requires-Dist: h5py>=3.1.0
Requires-Dist: jsonschema>=3.2.0
Requires-Dist: numpy>=1.19.3
Requires-Dist: pandas>=1.2.0
Requires-Dist: ruamel-yaml>=0.16
Provides-Extra: all
Requires-Dist: codespell; extra == 'all'
Requires-Dist: hdmf-zarr>=0.12.0; extra == 'all'
Requires-Dist: linkml-runtime>=1.5.5; extra == 'all'
Requires-Dist: matplotlib; extra == 'all'
Requires-Dist: numcodecs<0.16.0; extra == 'all'
Requires-Dist: oaklib>=0.5.12; extra == 'all'
Requires-Dist: pre-commit; extra == 'all'
Requires-Dist: pytest; extra == 'all'
Requires-Dist: pytest-cov; extra == 'all'
Requires-Dist: python-dateutil; extra == 'all'
Requires-Dist: pyyaml>=6.0.1; extra == 'all'
Requires-Dist: ruff; extra == 'all'
Requires-Dist: schemasheets>=0.4.0rc1; extra == 'all'
Requires-Dist: scipy>=1.7; extra == 'all'
Requires-Dist: sphinx-copybutton; extra == 'all'
Requires-Dist: sphinx-gallery; extra == 'all'
Requires-Dist: sphinx-rtd-theme>=1; extra == 'all'
Requires-Dist: sphinx>=4; extra == 'all'
Requires-Dist: tox; extra == 'all'
Requires-Dist: tqdm>=4.41.0; extra == 'all'
Requires-Dist: zarr<3,>=2.12.0; extra == 'all'
Provides-Extra: docs
Requires-Dist: matplotlib; extra == 'docs'
Requires-Dist: sphinx-copybutton; extra == 'docs'
Requires-Dist: sphinx-gallery; extra == 'docs'
Requires-Dist: sphinx-rtd-theme>=1; extra == 'docs'
Requires-Dist: sphinx>=4; extra == 'docs'
Provides-Extra: min-reqs
Requires-Dist: h5py==3.1.0; extra == 'min-reqs'
Requires-Dist: jsonschema==3.2.0; extra == 'min-reqs'
Requires-Dist: numpy==1.19.3; extra == 'min-reqs'
Requires-Dist: pandas==1.2.0; extra == 'min-reqs'
Requires-Dist: ruamel-yaml==0.16.0; extra == 'min-reqs'
Requires-Dist: scipy==1.7.0; extra == 'min-reqs'
Requires-Dist: tqdm==4.41.0; extra == 'min-reqs'
Requires-Dist: zarr==2.12.0; extra == 'min-reqs'
Provides-Extra: sparse
Requires-Dist: scipy>=1.7; extra == 'sparse'
Provides-Extra: termset
Requires-Dist: linkml-runtime>=1.5.5; extra == 'termset'
Requires-Dist: oaklib>=0.5.12; extra == 'termset'
Requires-Dist: pyyaml>=6.0.1; extra == 'termset'
Requires-Dist: schemasheets>=0.4.0rc1; extra == 'termset'
Provides-Extra: test
Requires-Dist: codespell; extra == 'test'
Requires-Dist: pre-commit; extra == 'test'
Requires-Dist: pytest; extra == 'test'
Requires-Dist: pytest-cov; extra == 'test'
Requires-Dist: python-dateutil; extra == 'test'
Requires-Dist: ruff; extra == 'test'
Requires-Dist: tox; extra == 'test'
Provides-Extra: tqdm
Requires-Dist: tqdm>=4.41.0; extra == 'tqdm'
Provides-Extra: zarr
Requires-Dist: hdmf-zarr>=0.12.0; extra == 'zarr'
Requires-Dist: numcodecs<0.16.0; extra == 'zarr'
Requires-Dist: zarr<3,>=2.12.0; extra == 'zarr'
